youtubecrawler/base.py
youtubecrawler/channel.py
youtubecrawler/crawl.py
youtubecrawler/synced.py
youtubecrawler/Asyncs/__init__.py
youtubecrawler/Asyncs/asynced.py
youtubecrawler/Asyncs/asyncedChannel.py
youtubecrawler-0.19.dist-info/METADATA
youtubecrawler-0.19.dist-info/WHEEL
youtubecrawler-0.19.dist-info/top_level.txt
youtubecrawler-0.19.dist-info/RECORD
