Metadata-Version: 2.1
Name: youtubecrawler
Version: 0.19
Summary: Youtube videos and channels scraper python wraper!
Home-page: UNKNOWN
Author: KeinShin
Author-email: <youtubecrawler@youtubecrawl.com>
License: UNKNOWN
Keywords: python,youtube,scraper,youtubevideodownload,channelscraper,youtubescraper
Platform: UNKNOWN
Classifier: Development Status :: 1 - Planning
Classifier: Intended Audience :: Developers
Classifier: Programming Language :: Python :: 3
Classifier: Operating System :: Unix
Classifier: Operating System :: MacOS :: MacOS X
Classifier: Operating System :: Microsoft :: Windows
Requires-Dist: moviepy
Requires-Dist: requests-html
Requires-Dist: bs4
Requires-Dist: lxml
Requires-Dist: pytube
